kg_qa/AGAPI.py
kg_qa/DataHubAPI.py
kg_qa/ExternalLink.py
kg_qa/Graph.py
kg_qa/GraphOfKG.gpickle
kg_qa/LODCloudAPI.py
kg_qa/LOVAPI.py
kg_qa/VoIDAnalyses.py
kg_qa/__init__.py
kg_qa/aggregator.py
kg_qa/availability.py
kg_qa/bloomfilter.py
kg_qa/knowledge_graph.py
kg_qa/licensing.py
kg_qa/lov1.txt
kg_qa/lov2.txt
kg_qa/query.py
kg_qa/resources.py
kg_qa/sources.py
kg_qa/utils.py
kg_qa-0.1.1.dist-info/METADATA
kg_qa-0.1.1.dist-info/WHEEL
kg_qa-0.1.1.dist-info/top_level.txt
kg_qa-0.1.1.dist-info/RECORD
